CMakeLists.txt
LICENSE
MANIFEST.in
README.rst
_cppsim_mpi.cpp
_cppstabsim.cpp
_sched_cpp.cpp
_setup.py
_version.py
requirements.txt
setup.py
cmake/ClangFormat.cmake
cmake/FindBPython.cmake
cmake/FindNOpenMP.cmake
cmake/FindPythonSupport.cmake
cmake/FindSphinx.cmake
cmake/Findgflags.cmake
cmake/Findglog.cmake
cmake/Findhwloc.cmake
cmake/Findxsimd.cmake
cmake/compiler_flags.cmake
cmake/macros.cmake
cmake/macros_more.cmake
cmake/options.cmake
cmake/os_detection.cmake
cmake/packages.cmake
pybind11/CMakeLists.txt
pybind11/include/pybind11/attr.h
pybind11/include/pybind11/buffer_info.h
pybind11/include/pybind11/cast.h
pybind11/include/pybind11/chrono.h
pybind11/include/pybind11/common.h
pybind11/include/pybind11/complex.h
pybind11/include/pybind11/eigen.h
pybind11/include/pybind11/embed.h
pybind11/include/pybind11/eval.h
pybind11/include/pybind11/functional.h
pybind11/include/pybind11/iostream.h
pybind11/include/pybind11/numpy.h
pybind11/include/pybind11/operators.h
pybind11/include/pybind11/options.h
pybind11/include/pybind11/pybind11.h
pybind11/include/pybind11/pytypes.h
pybind11/include/pybind11/stl.h
pybind11/include/pybind11/stl_bind.h
pybind11/include/pybind11/detail/class.h
pybind11/include/pybind11/detail/common.h
pybind11/include/pybind11/detail/descr.h
pybind11/include/pybind11/detail/init.h
pybind11/include/pybind11/detail/internals.h
pybind11/include/pybind11/detail/typeid.h
pybind11/pybind11/__init__.py
pybind11/pybind11/__main__.py
pybind11/pybind11/_version.py
pybind11/tools/FindCatch.cmake
pybind11/tools/FindEigen3.cmake
pybind11/tools/FindPythonLibsNew.cmake
pybind11/tools/check-style.sh
pybind11/tools/libsize.py
pybind11/tools/mkdoc.py
pybind11/tools/pybind11Config.cmake.in
pybind11/tools/pybind11Tools.cmake
python/hiq/__init__.py
python/hiq/libs/__init__.py
python/hiq/libs/_get_expectation_value.py
python/hiq/mitigation/__init__.py
python/hiq/mitigation/_extrapolation.py
python/hiq/noise/__init__.py
python/hiq/noise/_kraus_error.py
python/hiq_circuit.egg-info/PKG-INFO
python/hiq_circuit.egg-info/SOURCES.txt
python/hiq_circuit.egg-info/dependency_links.txt
python/hiq_circuit.egg-info/not-zip-safe
python/hiq_circuit.egg-info/requires.txt
python/hiq_circuit.egg-info/top_level.txt
