Metadata-Version: 1.0
Name: hiq-circuit
Version: 0.0.2.post4
Summary: A high performance distributed quantum simulator
Home-page: https://github.com/Huawei-HiQ/HiQsimulator
Author: hiq
Author-email: hiqinfo@huawei.com
License: Apache 2
Platform: UNKNOWN
